fps_inspector_sdk/__init__.py
fps_inspector_sdk/exit_codes.py
fps_inspector_sdk/fps_inspector.py
fps_inspector_sdk/lib/PresentMon.dll
fps_inspector_sdk-1.0.8.dist-info/METADATA
fps_inspector_sdk-1.0.8.dist-info/WHEEL
fps_inspector_sdk-1.0.8.dist-info/top_level.txt
fps_inspector_sdk-1.0.8.dist-info/zip-safe
fps_inspector_sdk-1.0.8.dist-info/RECORD
