Metadata-Version: 2.1
Name: fps-inspector-sdk
Version: 1.0.8
Summary: Library to measure FPS and FlipRate
Home-page: https://github.com/Andrey1994/fps_inspector_sdk
Author: Andrey Parfenov
Author-email: a1994ndrey@gmail.com
License: UNKNOWN
Platform: UNKNOWN
Classifier: Development Status :: 2 - Pre-Alpha
Classifier: Topic :: Utilities
Requires-Python: >=3
Requires-Dist: numpy
Requires-Dist: pandas
